LICENSE
MANIFEST.in
README.md
pyproject.toml
setup.cfg
setup.py
salaora/__init__.py
salaora/__main__.py
salaora/_version.py
salaora/manage.py
salaora.egg-info/PKG-INFO
salaora.egg-info/SOURCES.txt
salaora.egg-info/dependency_links.txt
salaora.egg-info/requires.txt
salaora.egg-info/top_level.txt
salaora/media/defaults/no_car.png
salaora/media/defaults/no_document.pdf
salaora/media/defaults/no_license.jpeg
salaora/reservations/__init__.py
salaora/reservations/admin.py
salaora/reservations/apps.py
salaora/reservations/forms.py
salaora/reservations/models.py
salaora/reservations/tests.py
salaora/reservations/urls.py
salaora/reservations/views.py
salaora/reservations/templates/crud_reservation.html
salaora/reservations/templates/reservations.html
salaora/salaora/__init__.py
salaora/salaora/asgi.py
salaora/salaora/context_processors.py
salaora/salaora/settings.py
salaora/salaora/urls.py
salaora/salaora/views.py
salaora/salaora/wsgi.py
salaora/salaora/templates/base.html
salaora/salaora/templates/index.html
salaora/static/datatables.css
salaora/static/datatables.js
salaora/static/datatables.min.css
salaora/static/datatables.min.js
salaora/vehicles/__init__.py
salaora/vehicles/admin.py
salaora/vehicles/apps.py
salaora/vehicles/forms.py
salaora/vehicles/models.py
salaora/vehicles/tests.py
salaora/vehicles/urls.py
salaora/vehicles/views.py
salaora/vehicles/templates/bulk_create_vehicles.html
salaora/vehicles/templates/vehicle.html
salaora/vehicles/templates/vehicles.html